cendas.py
cendas-0.0.3.dist-info/LICENSE.txt
cendas-0.0.3.dist-info/METADATA
cendas-0.0.3.dist-info/WHEEL
cendas-0.0.3.dist-info/top_level.txt
cendas-0.0.3.dist-info/RECORD
