Metadata-Version: 2.1
Name: cendas
Version: 0.0.3
Summary: Cendas is a new pandas-based software library optimized for analyzing data provided by U.S. government agencies.
Home-page: https://github.com/justinkim668/cendas
Author: Justin Kim
Author-email: jtk2141@columbia.edu
License: UNKNOWN
Platform: UNKNOWN
Requires-Dist: pandas
